engtools/__init__.py
engtools-0.2.dist-info/DESCRIPTION.rst
engtools-0.2.dist-info/METADATA
engtools-0.2.dist-info/RECORD
engtools-0.2.dist-info/WHEEL
engtools-0.2.dist-info/metadata.json
engtools-0.2.dist-info/top_level.txt
