Metadata-Version: 2.0
Name: engtools
Version: 0.2
Summary: Structural engineering related functions and tools.
Home-page: https://github.com/rspears74/engtools
Author: Randall Spears
Author-email: rspears690@gmail.com
License: MIT
Platform: UNKNOWN
Requires-Dist: prettytable
